dir_to_crx/__init__.py
dir_to_crx/create.py
dir_to_crx/crx-packer.py
dir_to_crx/crx3_pb2.py
dir_to_crx-1.0.4.dist-info/LICENSE
dir_to_crx-1.0.4.dist-info/METADATA
dir_to_crx-1.0.4.dist-info/WHEEL
dir_to_crx-1.0.4.dist-info/top_level.txt
dir_to_crx-1.0.4.dist-info/RECORD
