Metadata-Version: 2.1
Name: dir-to-crx
Version: 1.0.4
Summary: Convert directory to .crx for google extension
Home-page: https://github.com/chernyshev-aleksey/dir_fo_crx
Author: Aleksey Chernyshev
Author-email: chernyshev.prog@gmail.com
License: UNKNOWN
Platform: UNKNOWN
Classifier: Programming Language :: Python :: 3.6
Classifier: License :: OSI Approved :: MIT License
Classifier: Operating System :: OS Independent
Requires-Python: >=3.6
License-File: LICENSE
Requires-Dist: cryptography (>=37.0.2)
